LICENSE.txt
MANIFEST.in
README.rst
ez_setup.py
setup.cfg
setup.py
versioneer.py
doc/Makefile
doc/conf.py
doc/faq.rst
doc/index.rst
doc/installation.rst
doc/make.bat
doc/requirements.txt
doc/tutorial.rst
doc/useful_references.rst
doc/examples/fig_mymodel4.png
doc/examples/mymodel.dot
doc/examples/mymodel0.py
doc/examples/mymodel1.py
doc/examples/mymodel2.py
doc/examples/mymodel3.py
doc/examples/mymodel4.py
doc/examples/mymodel5.py
doc/examples/mymodel_fxns.py
doc/examples/robertson_standalone.py
doc/examples/test.png
doc/modules/bng.rst
doc/modules/core.rst
doc/modules/index.rst
doc/modules/integrate.rst
doc/modules/kappa.rst
doc/modules/macros.rst
doc/modules/modeltests.rst
doc/modules/pathfinder.rst
doc/modules/pattern.rst
doc/modules/simulator.rst
doc/modules/export/bng_net.rst
doc/modules/export/bngl.rst
doc/modules/export/index.rst
doc/modules/export/json.rst
doc/modules/export/kappa.rst
doc/modules/export/mathematica.rst
doc/modules/export/matlab.rst
doc/modules/export/potterswheel.rst
doc/modules/export/pysb_flat.rst
doc/modules/export/sbml.rst
doc/modules/export/stochkit.rst
doc/modules/importers/index.rst
doc/modules/tools/render.rst
doc/modules/tools/render_reactions.rst
doc/modules/tools/render_species.rst
doc/modules/tools/robertson_reactions.png
doc/modules/tools/sensitivity_analysis.rst
pysb/__init__.py
pysb/_version.py
pysb/anneal_mod.py
pysb/annotation.py
pysb/bng.py
pysb/builder.py
pysb/core.py
pysb/integrate.py
pysb/jacobian.py
pysb/kappa.py
pysb/logging.py
pysb/macros.py
pysb/pathfinder.py
pysb/pattern.py
pysb/util.py
pysb.egg-info/PKG-INFO
pysb.egg-info/SOURCES.txt
pysb.egg-info/dependency_links.txt
pysb.egg-info/requires.txt
pysb.egg-info/top_level.txt
pysb/examples/__init__.py
pysb/examples/bax_pore.py
pysb/examples/bax_pore_sequential.py
pysb/examples/bngwiki_egfr_simple.py
pysb/examples/bngwiki_enzymatic_cycle_mm.py
pysb/examples/bngwiki_simple.py
pysb/examples/earm_1_0.py
pysb/examples/earm_1_3.py
pysb/examples/explicit.py
pysb/examples/expression_observables.py
pysb/examples/fixed_initial.py
pysb/examples/fricker_2010_apoptosis.py
pysb/examples/hello_pysb.py
