Metadata-Version: 2.1
Name: pysb
Version: 1.15.0
Summary: Python Systems Biology modeling framework
Home-page: http://pysb.org/
Author: Jeremy Muhlich
Author-email: jmuhlich@bitflood.org
Keywords: systems,biology,model,rules
Classifier: Development Status :: 5 - Production/Stable
Classifier: Environment :: Console
Classifier: Intended Audience :: Science/Research
Classifier: License :: OSI Approved :: BSD License
Classifier: Operating System :: OS Independent
Classifier: Programming Language :: Python :: 3
Classifier: Topic :: Scientific/Engineering :: Bio-Informatics
Classifier: Topic :: Scientific/Engineering :: Chemistry
Classifier: Topic :: Scientific/Engineering :: Mathematics
Requires-Python: >=3.6
License-File: LICENSE.txt
